snek_dl/Snek.py
snek_dl/__init__.py
snek_dl/util.py
snek_dl-0.0.6.dist-info/LICENSE
snek_dl-0.0.6.dist-info/METADATA
snek_dl-0.0.6.dist-info/WHEEL
snek_dl-0.0.6.dist-info/top_level.txt
snek_dl-0.0.6.dist-info/RECORD
